docs_src/components/__init__.py
docs_src/components/demo_display.py
docs_src/components/navigation.py
docs_src/components/syntax_highlighting.py
docs_src/pages/__init__.py
docs_src/pages/home.py
docs_src/pages/not_found.py
docs_src/pages/demo/__init__.py
docs_src/pages/demo/fetch_sample.py
docs_src/pages/demo/fizzbuzz.py
docs_src/pages/demo/helloworld.py
docs_src/pages/demo/helloworld_classstyle.py
docs_src/pages/demo/matplotlib_sample.py
docs_src/pages/demo/todo.py
docs_src/pages/document/__init__.py
docs_src/pages/document/home.py
docs_src/templates/__init__.py
docs_src/templates/home.py
docs_src/templates/demo/__init__.py
docs_src/templates/demo/fetch_sample.py
docs_src/templates/demo/fizzbuzz.py
docs_src/templates/demo/helloworld.py
docs_src/templates/demo/helloworld_classstyle.py
docs_src/templates/demo/matplotlib_sample.py
docs_src/templates/demo/todo.py
docs_src/templates/document/__init__.py
docs_src/templates/document/home.py
webcompy/__init__.py
webcompy/__main__.py
webcompy/_version.py
webcompy/logging.py
webcompy/py.typed
webcompy/_browser/__init__.py
webcompy/_browser/_modules.py
webcompy/_browser/_modules.pyi
webcompy/_browser/_pyscript/__init__.py
webcompy/aio/__init__.py
webcompy/aio/_aio.py
webcompy/aio/_utils.py
webcompy/ajax/__init__.py
webcompy/ajax/_fetch.py
webcompy/app/__init__.py
webcompy/app/_app.py
webcompy/app/_root_component.py
webcompy/cli/__init__.py
webcompy/cli/_argparser.py
webcompy/cli/_asgi_app.py
webcompy/cli/_config.py
webcompy/cli/_exception.py
webcompy/cli/_generate.py
webcompy/cli/_html.py
webcompy/cli/_init_project.py
webcompy/cli/_pyscript_wheel.py
webcompy/cli/_server.py
webcompy/cli/_static_files.py
webcompy/cli/_utils.py
webcompy/cli/template_data/webcompy_config.py
webcompy/cli/template_data/app/__init__.py
webcompy/cli/template_data/app/bootstrap.py
webcompy/cli/template_data/app/router.py
webcompy/cli/template_data/app/components/__init__.py
webcompy/cli/template_data/app/components/fizzbuzz.py
webcompy-0.0.13.dist-info/LICENSE.txt
webcompy-0.0.13.dist-info/METADATA
webcompy-0.0.13.dist-info/WHEEL
webcompy-0.0.13.dist-info/top_level.txt
webcompy-0.0.13.dist-info/RECORD
