Metadata-Version: 2.1
Name: webcompy
Version: 0.0.13
Summary: Python frontend framework which works on Browser
Home-page: https://github.com/kniwase/WebComPy
Author: Kento Niwase
Author-email: kento.niwase@outlook.com
License: MIT
Keywords: browser,frontend,framework,front-end,client-side
Platform: UNKNOWN
Classifier: Programming Language :: Python :: 3.10
Classifier: Programming Language :: Python :: 3.9
Classifier: License :: OSI Approved :: MIT License
Classifier: Operating System :: OS Independent
License-File: LICENSE.txt
Requires-Dist: typing-extensions
Requires-Dist: wheel
Requires-Dist: starlette
Requires-Dist: sse-starlette
Requires-Dist: uvicorn
Requires-Dist: aiofiles
